Metadata-Version: 2.4
Name: assyst
Version: 0.11.0
Summary: Reference implentation of the Automated Small Symmetric Structure Training method.
Author-email: Marvin Poul <pmrv@posteo.de>
Project-URL: Repository, https://github.com/eisenforschung/assyst
Classifier: Programming Language :: Python :: 3
Classifier: Operating System :: OS Independent
Requires-Python: <3.14,>=3.11
License-File: LICENSE
Requires-Dist: pyxtal<1.2.0,>=1
Requires-Dist: tqdm<5,>=4
Requires-Dist: ase<4,>=3
Requires-Dist: matplotlib<4,>=3
Requires-Dist: numpy<3,>1
Requires-Dist: pandas<3,>=2.2
Requires-Dist: pyiron_snippets<2,>=1
Provides-Extra: test
Requires-Dist: pytest; extra == "test"
Requires-Dist: hypothesis; extra == "test"
Provides-Extra: doc
Requires-Dist: sphinx; extra == "doc"
Requires-Dist: furo; extra == "doc"
Provides-Extra: coverage
Requires-Dist: pytest; extra == "coverage"
Requires-Dist: pytest-cov; extra == "coverage"
Provides-Extra: grace
Requires-Dist: tensorpotential<0.5.8,>=0.5.1; extra == "grace"
Provides-Extra: plotneighborlist
Requires-Dist: matscipy<2,>=1; extra == "plotneighborlist"
Dynamic: license-file
